{
  "_class": "symbolMaster",
  "allowsOverrides": true,
  "backgroundColor": {
    "_class": "color",
    "alpha": 1,
    "blue": 0.2969547193877551,
    "green": 0.2969547193877551,
    "red": 0.2969547193877551
  },
  "booleanOperation": 0,
  "changeIdentifier": 13,
  "clippingMaskMode": 0,
  "do_objectID": "8FAA3C9D-7E5A-415A-811E-886FDD23A0D8",
  "exportOptions": {
    "_class": "exportOptions",
    "exportFormats": [
    ],
    "includedLayerIds": [
    ],
    "layerOptions": 0,
    "shouldTrim": false
  },
  "frame": {
    "_class": "rect",
    "constrainProportions": false,
    "height": 24,
    "width": 118,
    "x": 2631,
    "y": 0
  },
  "groupLayout": {
    "_class": "MSImmutableFreeformGroupLayout"
  },
  "hasBackgroundColor": true,
  "hasClickThrough": true,
  "hasClippingMask": false,
  "horizontalRulerData": {
    "_class": "rulerData",
    "base": 0,
    "guides": [
    ]
  },
  "includeBackgroundColorInExport": false,
  "includeBackgroundColorInInstance": false,
  "includeInCloudUpload": true,
  "isFixedToViewport": false,
  "isFlippedHorizontal": false,
  "isFlippedVertical": false,
  "isFlowHome": false,
  "isLocked": false,
  "isVisible": true,
  "layerListExpandedType": 0,
  "layers": [
    {
      "class": "rectangle",
      "id": "4B8CD351-1509-4E50-A71C-6266F57F7EDD"
    },
    {
      "class": "group",
      "id": "9CF4F7B3-D536-47AE-A5A1-696261AE5E5B"
    },
    {
      "class": "group",
      "id": "6D5B6EB7-EF02-4F59-A3F7-723E979BCCB8"
    },
    {
      "class": "group",
      "id": "5E04D475-153B-4D32-BFA6-94568C3B159D"
    },
    {
      "class": "group",
      "id": "88E49E42-4727-4268-9BD0-2B711EFF8C8B"
    }
  ],
  "name": "Bars/Status bar Content White",
  "nameIsFixed": true,
  "overrideProperties": [
    {
      "_class": "MSImmutableOverrideProperty",
      "canOverride": true,
      "overrideName": "33A116F7-3F72-4A9E-9250-299AD86D80A4_stringValue"
    }
  ],
  "resizesContent": false,
  "resizingConstraint": 63,
  "resizingType": 0,
  "rotation": 0,
  "shouldBreakMaskChain": true,
  "style": {
    "_class": "style",
    "endMarkerType": 0,
    "fills": [
      {
        "_class": "fill",
        "color": {
          "_class": "color",
          "alpha": 1,
          "blue": 1,
          "green": 1,
          "red": 1
        },
        "fillType": 0,
        "isEnabled": true,
        "noiseIndex": 0,
        "noiseIntensity": 0,
        "patternFillType": 1,
        "patternTileScale": 1
      }
    ],
    "miterLimit": 10,
    "startMarkerType": 0,
    "windingRule": 1
  },
  "symbolID": "F457B7D6-A719-4BAC-8FB9-DFED0F2B96F7",
  "userInfo": {
    "com.animaapp.stc-sketch-plugin": {
      "kModelPropertiesKey": {
      }
    }
  },
  "verticalRulerData": {
    "_class": "rulerData",
    "base": 0,
    "guides": [
    ]
  }
}