{
  "_class": "symbolInstance",
  "booleanOperation": -1,
  "clippingMaskMode": 0,
  "do_objectID": "049AE942-5DBF-4B17-A6A3-0AD4D0C1E8AD",
  "exportOptions": {
    "_class": "exportOptions",
    "do_objectID": "DDC3D9D8-4261-45BC-A420-2DD9CF062FE7",
    "exportFormats": [
    ],
    "includedLayerIds": [
    ],
    "layerOptions": 0,
    "shouldTrim": false
  },
  "frame": {
    "_class": "rect",
    "constrainProportions": false,
    "do_objectID": "7246916D-08CE-4D52-9CC2-3D9854B417C5",
    "height": 80,
    "width": 360,
    "x": 0,
    "y": 0
  },
  "hasClippingMask": false,
  "horizontalSpacing": 0,
  "isFixedToViewport": false,
  "isFlippedHorizontal": false,
  "isFlippedVertical": false,
  "isLocked": false,
  "isVisible": true,
  "layerListExpandedType": 0,
  "name": "Toolbar contents 2",
  "nameIsFixed": false,
  "overrideValues": [
    {
      "_class": "overrideValue",
      "do_objectID": "1228658B-BE3A-4547-8D48-5611F3A9F390",
      "overrideName": "C6DCFD59-E567-4A87-9991-850294011079_symbolID",
      "value": ""
    }
  ],
  "resizingConstraint": 63,
  "resizingType": 0,
  "rotation": 0,
  "scale": 1,
  "shouldBreakMaskChain": false,
  "style": {
    "_class": "style",
    "do_objectID": "28FFB40D-87FF-41B6-95DE-64E80967AB57",
    "endMarkerType": 0,
    "miterLimit": 10,
    "startMarkerType": 0,
    "windingRule": 1
  },
  "symbolID": "80684455-ABBC-4B34-A9B7-7F7EA56CA5C1",
  "userInfo": {
    "com.animaapp.stc-sketch-plugin": {
      "kModelPropertiesKey": {
      }
    }
  },
  "verticalSpacing": 0
}